dspace_requests_wrapper/__init__.py
dspace_requests_wrapper/py.typed
dspace_requests_wrapper-1.0.3.dist-info/METADATA
dspace_requests_wrapper-1.0.3.dist-info/WHEEL
dspace_requests_wrapper-1.0.3.dist-info/licenses/LICENSE
dspace_requests_wrapper-1.0.3.dist-info/RECORD
