Metadata-Version: 2.4
Name: dspace-requests-wrapper
Version: 1.0.3
Summary: A wrapper around the requests session object to make interacting with the DSpace API easier
Project-URL: Homepage, https://github.com/cu-library/dspace-requests-wrapper
Project-URL: Issues, https://github.com/cu-library/dspace-requests-wrapper/issues
Author-email: Kevin Bowrin <kevinbowrin@cunet.carleton.ca>
License-Expression: MIT
License-File: LICENSE
Requires-Python: >=3.9
Requires-Dist: requests>=2.32.4
